README.md
setup.py
src/clu_stress.egg-info/PKG-INFO
src/clu_stress.egg-info/SOURCES.txt
src/clu_stress.egg-info/dependency_links.txt
src/clu_stress.egg-info/requires.txt
src/clu_stress.egg-info/top_level.txt
src/clustress/__init__.py
src/clustress/accuracy_examples.py
src/clustress/clu_stress.py
src/clustress/distance_matrices_new.py
src/clustress/distance_matrix.py
src/clustress/earthquake_fms.py
src/clustress/main.py
tests/test_CluStress.py