Metadata-Version: 2.1
Name: clu-stress
Version: 1.0.0
Summary: A non-parametric clustering algorithm.
Home-page: https://github.com/lukacskuslits/clu-stress
Author: Lukacs Kuslits
Author-email: kuslits.lukacs@epss.hun-ren.hu
Classifier: Programming Language :: Python :: 3
Classifier: License :: OSI Approved :: MIT License
Classifier: Operating System :: OS Independent
Requires-Python: >=3.5
